kvvliveapi/KVV.py
kvvliveapi/__init__.py
kvvliveapi/__main__.py
kvvliveapi-0.2.1.dist-info/METADATA
kvvliveapi-0.2.1.dist-info/WHEEL
kvvliveapi-0.2.1.dist-info/top_level.txt
kvvliveapi-0.2.1.dist-info/RECORD
