Metadata-Version: 2.1
Name: kvvliveapi
Version: 0.2.1
Summary: KVV live API bindings
Home-page: https://github.com/Nervengift/kvvliveapi
Author: Nervengift
Author-email: github@nervengiftlabs.de
License: UNKNOWN
Keywords: kvv api
Platform: UNKNOWN
Requires-Dist: docopt
Requires-Dist: requests
